Randomfunctionwork.py
__init__.py
main.py
mastermind_fg-0.0.1.dist-info/METADATA
mastermind_fg-0.0.1.dist-info/WHEEL
mastermind_fg-0.0.1.dist-info/licenses/LICENSE .txt
mastermind_fg-0.0.1.dist-info/RECORD
