Metadata-Version: 2.1
Name: mastermind_FG
Version: 0.0.1
Summary: Project from a python class
Project-URL: Homepage, https://github.com/pypa/sampleproject
Project-URL: Bug Tracker, https://github.com/pypa/sampleproject/issues
Author-email: farid gerami <mr.maldo@gmail.com>
License-File: LICENSE .txt
Classifier: License :: OSI Approved :: MIT License
Classifier: Operating System :: OS Independent
Classifier: Programming Language :: Python :: 3
Requires-Python: >=3.10
